corpus_writer/__init__.py
corpus_writer/dumper.py
corpus_writer/logger.py
corpus_writer/writer.py
corpus_writer-0.0.5.dist-info/METADATA
corpus_writer-0.0.5.dist-info/WHEEL
corpus_writer-0.0.5.dist-info/RECORD
